physiokit/__init__.py
physiokit/ecg/__init__.py
physiokit/ecg/clean.py
physiokit/ecg/defines.py
physiokit/ecg/metrics.py
physiokit/ecg/noise.py
physiokit/ecg/peaks.py
physiokit/ecg/segment.py
physiokit/ecg/synthesize.py
physiokit/ecg/synthetic/__init__.py
physiokit/ecg/synthetic/defines.py
physiokit/ecg/synthetic/helper_functions.py
physiokit/ecg/synthetic/presets.py
physiokit/ecg/synthetic/rhythm_generator.py
physiokit/ecg/synthetic/wave_generator.py
physiokit/hrv/__init__.py
physiokit/hrv/defines.py
physiokit/hrv/frequency.py
physiokit/hrv/time.py
physiokit/imu/__init__.py
physiokit/imu/clean.py
physiokit/imu/metrics.py
physiokit/ppg/__init__.py
physiokit/ppg/clean.py
physiokit/ppg/defines.py
physiokit/ppg/metrics.py
physiokit/ppg/noise.py
physiokit/ppg/peaks.py
physiokit/ppg/synthesize.py
physiokit/rsp/__init__.py
physiokit/rsp/clean.py
physiokit/rsp/defines.py
physiokit/rsp/metrics.py
physiokit/rsp/noise.py
physiokit/rsp/peaks.py
physiokit/rsp/synthesize.py
physiokit/signal/__init__.py
physiokit/signal/distort.py
physiokit/signal/filter.py
physiokit/signal/noise.py
physiokit/signal/smooth.py
physiokit/signal/transform.py
physiokit-0.11.0.dist-info/licenses/LICENSE
physiokit-0.11.0.dist-info/METADATA
physiokit-0.11.0.dist-info/WHEEL
physiokit-0.11.0.dist-info/top_level.txt
physiokit-0.11.0.dist-info/RECORD
