Metadata-Version: 2.4
Name: physiokit
Version: 0.11.0
Summary: physioKIT, process raw ambulatory bio-signals.
Author-email: Ambiq AI <support.aitg@ambiq.com>
License: BSD-3-Clause
Project-URL: Homepage, https://ambiqai.github.io/physiokit
Project-URL: Source, https://github.com/AmbiqAI/physiokit
Keywords: physiology,bio-signals,ambulatory,wearables
Classifier: Programming Language :: Python :: 3
Classifier: Programming Language :: Python :: 3 :: Only
Classifier: Programming Language :: Python :: 3.12
Classifier: Programming Language :: Python :: 3.13
Classifier: Programming Language :: Python :: 3.14
Requires-Python: <3.15,>=3.12
License-File: LICENSE
Requires-Dist: numpy<3.0,>=2.1.1
Requires-Dist: scipy<2.0,>=1.14.1
Requires-Dist: requests<3.0,>=2.32.4
Dynamic: license-file
